mars_clock/Ls_utils.py
mars_clock/__init__.py
mars_clock/mission_sols.py
mars_clock/data/Piqueux2015_Table1.csv
tests/__init__.py
tests/test_mars_clock.py
mars_clock-0.2.4.dist-info/LICENSE
mars_clock-0.2.4.dist-info/METADATA
mars_clock-0.2.4.dist-info/WHEEL
mars_clock-0.2.4.dist-info/top_level.txt
mars_clock-0.2.4.dist-info/RECORD
